sorted_in_disk/__init__.py
sorted_in_disk/sorted_in_disk.py
sorted_in_disk/utils.py
sorted_in_disk-1.0.3.dist-info/LICENSE
sorted_in_disk-1.0.3.dist-info/METADATA
sorted_in_disk-1.0.3.dist-info/WHEEL
sorted_in_disk-1.0.3.dist-info/top_level.txt
sorted_in_disk-1.0.3.dist-info/RECORD
