Metadata-Version: 2.1
Name: sorted-in-disk
Version: 1.0.3
Summary: Sort a bulk of data in disk and parallel (RAM memory free)
Home-page: https://github.com/Invarato/sort_in_disk_project
Author: Ramon Invarato Menendez
Author-email: r.invarato@gmail.com
License: UNKNOWN
Platform: UNKNOWN
Classifier: Programming Language :: Python :: 3
Classifier: License :: OSI Approved :: MIT License
Classifier: Operating System :: OS Independent
Requires-Python: >=3.0
Requires-Dist: easy-binary-file (>=1.0.4)
Requires-Dist: quick-queue (>=1.0.5)
